{
	"ulid": "01JFPCDGNW8G72HJTFK0YAC32A",
	"minTime": 1734761312990,
	"maxTime": 1734825600000,
	"stats": {
		"numSamples": 50996,
		"numSeries": 1159,
		"numChunks": 10431
	},
	"compaction": {
		"level": 3,
		"sources": [
			"01JFM87R7CYM5JA2PDY8JSVGH6",
			"01JFME4Y8DV8QN18DMJJF4PH39",
			"01JFMN8H49JG278EX4DTPCM5D6",
			"01JFMW7WJ9XG3XE7Q0DAF14K7F",
			"01JFN35VN50B53RJCP7DEEC9VP",
			"01JFNA554VZA1R66MNWGZX0TGX",
			"01JFNH4KZV7CZ2G1S4KKH1Q5AV",
			"01JFNR41Z5VKSJJ4MSGC4SGSCG",
			"01JFNYNNYGWEYSEMWBYTD2SAH7"
		],
		"parents": [
			{
				"ulid": "01JFN35WAPH62P3BJN1AHNBH33",
				"minTime": 1734761312990,
				"maxTime": 1734782400000
			},
			{
				"ulid": "01JFNR42QCC9HYAVVMS5ZEP6T9",
				"minTime": 1734782834174,
				"maxTime": 1734804000000
			},
			{
				"ulid": "01JFPCDG01VF7XJFVPB9SQWAWT",
				"minTime": 1734804684572,
				"maxTime": 1734825600000
			}
		]
	},
	"version": 1
}