{
	"ulid": "01JFGJYD5V2JNQXQ5NDS20HPX9",
	"minTime": 1734566752239,
	"maxTime": 1734631200000,
	"stats": {
		"numSamples": 36621,
		"numSeries": 939,
		"numChunks": 8451
	},
	"compaction": {
		"level": 3,
		"sources": [
			"01JFEETJY290CZAE68TTSKWBN6",
			"01JFEN9PH5FFDXZMH9D92MSN9Z",
			"01JFEWQGTQQMAN5CYV1P1BY23X",
			"01JFF3JN379HE6SZP03TWBW5EM",
			"01JFFAMV3H3728Y2PZXZBPJDM0",
			"01JFFGKS37405ZS5V1X0QVWGEM",
			"01JFFQK57VDCAVM4ZQNAYX7G5S",
			"01JFFXWRHTD3YAQYM7GZT890GT",
			"01JFG5J3APNJB6NY0J1F2R7QC4"
		],
		"parents": [
			{
				"ulid": "01JFFAMVM2MB9EYA1BQFH79NSF",
				"minTime": 1734566752239,
				"maxTime": 1734588000000
			},
			{
				"ulid": "01JFFXWS7WF7PB7D2S6MH054SM",
				"minTime": 1734588041063,
				"maxTime": 1734609600000
			},
			{
				"ulid": "01JFGJYCHJ5VDH5GWZ7C7ZZQ64",
				"minTime": 1734610127434,
				"maxTime": 1734631200000
			}
		]
	},
	"version": 1
}